tech_insights_extractor/__init__.py
tech_insights_extractor/main.py
tech_insights_extractor/prompts.py
tech_insights_extractor-2025.12.21230046.dist-info/METADATA
tech_insights_extractor-2025.12.21230046.dist-info/WHEEL
tech_insights_extractor-2025.12.21230046.dist-info/top_level.txt
tech_insights_extractor-2025.12.21230046.dist-info/RECORD
