Metadata-Version: 2.4
Name: tech-insights-extractor
Version: 2025.12.21230046
Summary: tech-insights-extractor summarizes tech breakthroughs, extracts key innovations, and categorizes advances from user text using LLM prompts.
Author-email: tech-insights-extractor <hi@eugene.plus>
License: MIT
Project-URL: Homepage, https://github.com/chigwell/tech-insights-extractor
Requires-Python: >=3.9
Requires-Dist: langchain-llm7>=0.0.0
Requires-Dist: llmatch-messages>=0.0.0
Requires-Dist: langchain-core>=0.3.0
